[
  {
    "name": "primary",
    "shades": [
      "#f5f6fc",
      "#cdd3f1",
      "#a5b0e6",
      "#7d8edc",
      "#566bd1",
      "#2e48c6",
      "#273da8",
      "#20328b",
      "#19286d",
      "#121d4f"
    ]
  },
  {
    "name": "secondary",
    "shades": [
      "#f2f9f8",
      "#c2e1dd",
      "#91c9c2",
      "#61b2a8",
      "#309a8d",
      "#008272",
      "#006f61",
      "#005b50",
      "#00483f",
      "#00342e"
    ]
  },
  {
    "name": "tertiary",
    "shades": [
      "#f8f9fb",
      "#dee4ed",
      "#c4cfe0",
      "#a9bad2",
      "#8fa4c4",
      "#758fb6",
      "#637a9b",
      "#52647f",
      "#404f64",
      "#2f3949"
    ]
  },
  {
    "name": "red",
    "shades": [
      "#fdf5f5",
      "#f4cecf",
      "#eba8a9",
      "#e28184",
      "#da5b5e",
      "#d13438",
      "#b22c30",
      "#922427",
      "#731d1f",
      "#541516"
    ]
  },
  {
    "name": "orange",
    "shades": [
      "#fdf7f2",
      "#f5d8c2",
      "#edb991",
      "#e49a61",
      "#dc7b30",
      "#d45c00",
      "#b44e00",
      "#944000",
      "#753300",
      "#552500"
    ]
  },
  {
    "name": "green",
    "shades": [
      "#f7fbf3",
      "#d9eac4",
      "#bbda96",
      "#9cca67",
      "#7eb939",
      "#60a90a",
      "#529009",
      "#437607",
      "#355d06",
      "#264404"
    ]
  },
  {
    "name": "blue",
    "shades": [
      "#f3f8fc",
      "#c6dcef",
      "#98c1e3",
      "#6ba5d7",
      "#3d8aca",
      "#106ebe",
      "#0e5ea2",
      "#0b4d85",
      "#093d69",
      "#062c4c"
    ]
  },
  {
    "name": "black",
    "shades": [
      "#ffffff",
      "#F5F5F5",
      "#EEEEEE",
      "#E0E0E0",
      "#BDBDBD",
      "#9E9E9E",
      "#757575",
      "#616161",
      "#424242",
      "#000000"
    ]
  }
]
